OpenglJiaocheng/README.md
OpenglJiaocheng/__init__.py
OpenglJiaocheng/__main__.py
OpenglJiaocheng/file.epub
OpenglJiaocheng/index.html
OpenglJiaocheng/css/__init__.py
OpenglJiaocheng/css/annotations.css
OpenglJiaocheng/css/main.css
OpenglJiaocheng/css/normalize.css
OpenglJiaocheng/css/popup.css
OpenglJiaocheng/font/__init__.py
OpenglJiaocheng/font/fontello.eot
OpenglJiaocheng/font/fontello.svg
OpenglJiaocheng/font/fontello.ttf
OpenglJiaocheng/font/fontello.woff
OpenglJiaocheng/img/__init__.py
OpenglJiaocheng/img/annotator-glyph-sprite.png
OpenglJiaocheng/img/annotator-icon-sprite.png
OpenglJiaocheng/img/apple-touch-icon.png
OpenglJiaocheng/img/cancelfullscreen.png
OpenglJiaocheng/img/close.png
OpenglJiaocheng/img/fullscreen.png
OpenglJiaocheng/img/loader.gif
OpenglJiaocheng/img/menu-icon.png
OpenglJiaocheng/img/save.png
OpenglJiaocheng/img/saved.png
OpenglJiaocheng/img/settings-s.png
OpenglJiaocheng/img/settings.png
OpenglJiaocheng/img/star.png
OpenglJiaocheng/js/__init__.py
OpenglJiaocheng/js/epub.js
OpenglJiaocheng/js/epub.min.js
OpenglJiaocheng/js/epub.min.map
OpenglJiaocheng/js/hooks.min.js
OpenglJiaocheng/js/hooks.min.map
OpenglJiaocheng/js/reader.js
OpenglJiaocheng/js/reader.js.map
OpenglJiaocheng/js/reader.min.js
OpenglJiaocheng/js/reader.min.map
OpenglJiaocheng/js/hooks/__init__.py
OpenglJiaocheng/js/hooks/extensions/__init__.py
OpenglJiaocheng/js/hooks/extensions/highlight.js
OpenglJiaocheng/js/libs/__init__.py
OpenglJiaocheng/js/libs/jquery.min.js
OpenglJiaocheng/js/libs/localforage.min.js
OpenglJiaocheng/js/libs/screenfull.js
OpenglJiaocheng/js/libs/screenfull.min.js
OpenglJiaocheng/js/libs/zip.min.js
OpenglJiaocheng/js/plugins/__init__.py
OpenglJiaocheng/js/plugins/hypothesis.js
OpenglJiaocheng/js/plugins/search.js
opengl_jiaocheng-2024.3.2.0.dist-info/METADATA
opengl_jiaocheng-2024.3.2.0.dist-info/WHEEL
opengl_jiaocheng-2024.3.2.0.dist-info/entry_points.txt
opengl_jiaocheng-2024.3.2.0.dist-info/top_level.txt
opengl_jiaocheng-2024.3.2.0.dist-info/RECORD
